genotate/__init__.py
genotate/bacteria0.data-00000-of-00001
genotate/bacteria0.index
genotate/bacteria1.data-00000-of-00001
genotate/bacteria1.index
genotate/bacteria2.data-00000-of-00001
genotate/bacteria2.index
genotate/bacteria3.data-00000-of-00001
genotate/bacteria3.index
genotate/bacteria4.data-00000-of-00001
genotate/bacteria4.index
genotate/codons.py
genotate/dump_weights.py
genotate/feature.py
genotate/file.py
genotate/functions.py
genotate/locus.py
genotate/make_model.py
genotate/make_train.py
genotate/phage0.data-00000-of-00001
genotate/phage0.index
genotate/phage1.data-00000-of-00001
genotate/phage1.index
genotate/phage2.data-00000-of-00001
genotate/phage2.index
genotate/phage3.data-00000-of-00001
genotate/phage3.index
genotate/phage4.data-00000-of-00001
genotate/phage4.index
genotate/predict.py
genotate/windows.cpython-39-darwin.so
genotate-0.17.data/scripts/genotate.py
genotate-0.17.dist-info/licenses/LICENSE
genotate-0.17.dist-info/METADATA
genotate-0.17.dist-info/WHEEL
genotate-0.17.dist-info/top_level.txt
genotate-0.17.dist-info/RECORD
