Metadata-Version: 2.4
Name: genotate
Version: 0.17
Summary: A tool to annotate microbial genomes
Home-page: https://github.com/deprekate/genotate
Author: Katelyn McNair
Author-email: deprekate@gmail.com
Classifier: Programming Language :: Python :: 3
Classifier: License :: OSI Approved :: GNU General Public License v3 or later (GPLv3+)
Classifier: Operating System :: OS Independent
Requires-Python: >3.5.2
License-File: LICENSE
Requires-Dist: genbank
Requires-Dist: numpy
Requires-Dist: ruptures
Requires-Dist: tensorflow
Dynamic: author
Dynamic: author-email
Dynamic: classifier
Dynamic: description
Dynamic: description-content-type
Dynamic: home-page
Dynamic: license-file
Dynamic: requires-dist
Dynamic: requires-python
Dynamic: summary
